nautilus/__init__.py
nautilus/neural.py
nautilus/pool.py
nautilus/prior.py
nautilus/sampler.py
nautilus/bounds/__init__.py
nautilus/bounds/basic.py
nautilus/bounds/nautilus.py
nautilus/bounds/neural.py
nautilus/bounds/periodic.py
nautilus/bounds/union.py
nautilus_sampler-1.0.6.dist-info/licenses/LICENSE
nautilus_sampler-1.0.6.dist-info/WHEEL
nautilus_sampler-1.0.6.dist-info/METADATA
nautilus_sampler-1.0.6.dist-info/RECORD
