Metadata-Version: 2.4
Name: nautilus-sampler
Version: 1.0.6
Summary: Neural Network-Boosted Importance Sampling for Bayesian Statistics.
Author-email: "Johannes U. Lange" <jlange@american.edu>
Requires-Python: >= 3.9
Classifier: License :: OSI Approved :: MIT License
License-File: LICENSE
Requires-Dist: numpy>=1.18.0
Requires-Dist: scipy>=1.4.0
Requires-Dist: scikit-learn>=0.22.0
Requires-Dist: threadpoolctl>=3.0.0
Requires-Dist: h5py>=3.0.0 ; extra == "checkpointing"
Requires-Dist: h5py>=3.0.0 ; extra == "tests"
Requires-Dist: dask[distributed]>=2022.2.0 ; extra == "tests"
Project-URL: Home, https://nautilus-sampler.readthedocs.io
Provides-Extra: checkpointing
Provides-Extra: tests
